handles/__init__.py
handles/__main__.py
handles/cli.py
handles/mapping.py
handles/platform.py
handles/platforms/__init__.py
handles/platforms/github.py
handles/platforms/instagram.py
handles/platforms/medium.py
handles/platforms/npm.py
handles/platforms/youtube.py
handles-0.1.1.dist-info/METADATA
handles-0.1.1.dist-info/WHEEL
handles-0.1.1.dist-info/entry_points.txt
handles-0.1.1.dist-info/licenses/LICENSE
handles-0.1.1.dist-info/RECORD
