Metadata-Version: 2.3
Name: handles
Version: 0.1.1
Summary: Command-line tool to check the availability of a username on various platforms.
Project-URL: Homepage, https://github.com/4mbl/handles
Project-URL: Bug Tracker, https://github.com/4mbl/handles/issues
Project-URL: Documentation, https://github.com/4mbl/handles/blob/main/README.md
Project-URL: Repository, https://github.com/4mbl/handles
Author: 4MBL
License: MIT License
License-File: LICENSE
Keywords: CLI,handle,social media,username
Classifier: Development Status :: 5 - Production/Stable
Classifier: Environment :: Console
Classifier: Intended Audience :: Developers
Classifier: License :: OSI Approved :: MIT License
Classifier: Natural Language :: English
Classifier: Operating System :: OS Independent
Classifier: Programming Language :: Python :: 3
Classifier: Programming Language :: Python :: 3.9
Classifier: Programming Language :: Python :: 3.10
Classifier: Programming Language :: Python :: 3.11
Classifier: Programming Language :: Python :: 3.12
Classifier: Programming Language :: Python :: 3.13
Classifier: Programming Language :: Python :: Implementation :: CPython
Classifier: Topic :: Software Development
Classifier: Typing :: Typed
Requires-Python: >=3.9
Requires-Dist: requests<2.33.0,>=2.32.0
